MANIFEST.in
README.md
pyhash.py
requirements.txt
setup.py
hvnpyhash.egg-info/PKG-INFO
hvnpyhash.egg-info/SOURCES.txt
hvnpyhash.egg-info/dependency_links.txt
hvnpyhash.egg-info/top_level.txt
src/CityHash.h
src/FNV1.h
src/FarmHash.h
src/Hash.cpp
src/Hash.h
src/Lookup3.h
src/MetroHash.h
src/Mum.h
src/MurmurHash.h
src/SpookyHash.h
src/SuperFastHash.h
src/T1.h
src/xxHash.h
src/SuperFastHash/SuperFastHash.c
src/fnv/fnv.h
src/fnv/fnv32.c
src/fnv/fnv64.c
src/fnv/hash_32.c
src/fnv/hash_32a.c
src/fnv/hash_64.c
src/fnv/hash_64a.c
src/fnv/have_ulong64.c
src/fnv/longlong.h
src/fnv/test_fnv.c
src/lookup3/lookup3.c