Metadata-Version: 1.1
Name: hvnpyhash
Version: 0.8.1
Summary: Python Non-cryptographic Hash Library
Home-page: https://github.com/flier/pyfasthash
Author: Flier Lu
Author-email: flier.lu@gmail.com
License: Apache Software License
Download-URL: https://github.com/flier/pyfasthash/releases
Keywords: hash hashing fasthash
Platform: x86
Platform: x64
Classifier: Development Status :: 4 - Beta
Classifier: Intended Audience :: Developers
Classifier: Intended Audience :: System Administrators
Classifier: License :: OSI Approved :: Apache Software License
Classifier: Natural Language :: English
Classifier: Operating System :: Microsoft :: Windows
Classifier: Operating System :: POSIX
Classifier: Programming Language :: C++
Classifier: Programming Language :: Python
Classifier: Programming Language :: Python :: 2
Classifier: Programming Language :: Python :: 3
Classifier: Topic :: Internet
Classifier: Topic :: Software Development
Classifier: Topic :: Software Development :: Libraries :: Python Modules
Classifier: Topic :: Utilities
